{"key":"get_financials:{\"query\":\"AAPL balance sheet\"}","value":"{\"data\":{\"get_balance_sheets_AAPL\":[{\"ticker\":\"AAPL\",\"report_period\":\"2025-09-27\",\"fiscal_period\":\"2025-FY\",\"filing_url\":\"https://www.sec.gov/Archives/edgar/data/320193/000032019325000079/aapl-20250927.htm\",\"total_assets\":359241000000,\"current_assets\":147957000000,\"cash_and_equivalents\":35934000000,\"inventory\":5718000000,\"current_investments\":18763000000,\"trade_and_non_trade_receivables\":72957000000,\"non_current_assets\":211284000000,\"property_plant_and_equipment\":49834000000,\"goodwill_and_intangible_assets\":0,\"investments\":96486000000,\"non_current_investments\":77723000000,\"tax_assets\":0,\"total_liabilities\":285508000000,\"current_liabilities\":165631000000,\"current_debt\":20329000000,\"trade_and_non_trade_payables\":69860000000,\"deferred_revenue\":9055000000,\"deposit_liabilities\":0,\"non_current_liabilities\":119877000000,\"non_current_debt\":78328000000,\"tax_liabilities\":0,\"shareholders_equity\":73733000000,\"retained_earnings\":-14264000000,\"accumulated_other_comprehensive_income\":-5571000000,\"outstanding_shares\":14840390000,\"total_debt\":98657000000}]},\"sourceUrls\":[\"https://api.financialdatasets.ai/financials/balance-sheets/?ticker=AAPL&period=annual&limit=1\"]}","expiresAt":1774900517246,"toolName":"get_financials","savedAt":"2026-03-30T19:40:17.246Z"}