{"key":"get_financials:{\"query\":\"Apple (AAPL) financials\"}","value":"{\"data\":{\"get_key_ratios_AAPL\":{\"ticker\":\"AAPL\",\"market_cap\":3639859034490,\"enterprise_value\":3685051034490,\"price_to_book_ratio\":41.27292249109876,\"price_to_earnings_ratio\":30.975784690389467,\"price_to_sales_ratio\":8.355640469701596,\"enterprise_value_to_ebitda_ratio\":24.08860715843351,\"enterprise_value_to_revenue_ratio\":8.459382977454966,\"free_cash_flow_yield\":0.03388153190313854,\"peg_ratio\":4.744771048887511,\"gross_margin\":0.4732528803972297,\"operating_margin\":0.3240162803563681,\"net_margin\":0.27036823631768275,\"return_on_equity\":1.3354915523301962,\"return_on_assets\":0.3105139244444327,\"return_on_invested_capital\":0.8359908383440044,\"asset_turnover\":1.1796738962653242,\"inventory_turnover\":75.15172949193479,\"receivables_turnover\":6.080766626883589,\"days_sales_outstanding\":0.1644529483468276,\"operating_cycle\":81.23249611881837,\"working_capital_turnover\":12.5411544551605,\"current_ratio\":0.9737446648641658,\"quick_ratio\":0.9375612039392242,\"cash_ratio\":0.27910228063584347,\"operating_cash_flow_ratio\":0.8343567350508416,\"debt_to_equity\":1.0262954983558226,\"debt_to_assets\":0.23862303155574655,\"interest_coverage\":null,\"revenue_growth\":0.046751137180081746,\"earnings_growth\":0.051486474421926616,\"book_value_growth\":0.19607231497429917,\"earnings_per_share_growth\":0.06528404504923846,\"free_cash_flow_growth\":0.2486356779086132,\"operating_income_growth\":0.06342246231042199,\"ebitda_growth\":0.059213304991448966,\"payout_ratio\":0.13148577396265823,\"earnings_per_share\":7.952340916045502,\"book_value_per_share\":5.9546171611269845,\"free_cash_flow_per_share\":8.32687613991183}},\"sourceUrls\":[\"https://api.financialdatasets.ai/financial-metrics/snapshot/?ticker=AAPL\"]}","expiresAt":1774901196283,"toolName":"get_financials","savedAt":"2026-03-30T19:51:36.283Z"}