{"key":"markov_distribution:{\"currentPrice\":414.58,\"historicalPrices\":[421.29,437.23,443.6,451.79,458,464.7,476.1,494.56,495.9,444.95,427.13,454.29,453.97,441.88,455.46,467.03,462.4,467.63,451.39,462.62,448.2,458.28,459.56,468.62,481.28,474.61,473.42,477.48,483.75,490,468.14,471.8,466.13,473.51,472.53,477.86,476.24,466.88,460.84,460.43,459.27,444.74,426.41,413.38,404.04,404.13,416.29,400.64,414.7,414.58],\"horizon\":30,\"polymarketMarkets\":[{\"probability\":0.284,\"question\":\"Will Gold (GC) hit (HIGH) $5,500 by end of June?\",\"volume\":8000},{\"probability\":0.125,\"question\":\"Will Gold (GC) hit (HIGH) $6,000 by end of June?\",\"volume\":6000},{\"probability\":0.031,\"question\":\"Will Gold (GC) hit (HIGH) $7,000 by end of June?\",\"volume\":6000},{\"probability\":0.083,\"question\":\"Will Gold (GC) hit (LOW) $3,400 by end of June?\",\"volume\":6000}],\"ticker\":\"GLD\"}","value":"📊 Markov Distribution: GLD | Horizon: 30d\nCurrent: $414.58 | Regime: sideways\nAnchors: 0 (trusted) | Sentiment shift: 0%\nMixing weight: 0% Markov / 100% Anchors\n⚠️ Structural break detected (divergence=1.418); CI widened 50%, using default matrix\n⚠️ Sparse states (<5 obs): bear — transitions prior-dominated\n📋 Decision Summary\n────────────────────────────────────────────────────────────\n📈 BUY    (>+5%)        16.5%   P(price exceeds current +5% by horizon)\n➡️  HOLD   (±3%..+5%)    57.9%   P(price stays range-bound)\n📉 SELL   (<−3%)        25.6%   P(price falls more than −3% by horizon)\n➡️  Recommendation: HOLD  [HIGH confidence]\n   Expected return: +0.2%  |  Risk/reward: 1.14×  (>1 = upside larger than downside)\nPrice         P(>price)    90% CI                 Source\n────────────────────────────────────────────────────────────\n$   356.43    99.9%   [99.7%–100.0%]   markov\n$   361.81    99.8%   [99.4%–100.0%]   markov\n$   367.28    99.4%   [98.7%–100.0%]   markov\n$   372.83    98.7%   [97.3%–99.8%]   markov\n$   378.47    97.2%   [94.9%–99.2%]   markov\n$   384.19    94.6%   [91.0%–97.8%]   markov\n$   390.00    90.2%   [85.3%–94.8%]   markov\n$   395.89    83.7%   [77.6%–89.8%]   markov\n$   401.87    74.9%   [68.0%–82.0%]   markov\n$   407.95    64.1%   [56.7%–71.6%]   markov\n$   414.11    52.0%   [44.4%–59.7%]   markov\n$   420.37    39.7%   [32.3%–47.3%]   markov\n$   426.73    28.4%   [21.3%–35.7%]   markov\n$   433.18    18.9%   [12.6%–25.4%]   markov\n$   439.72    11.6%   [6.7%–17.0%]   markov\n$   446.37     6.6%   [3.1%–10.6%]   markov\n$   453.12     3.5%   [1.2%–6.2%]   markov\n$   459.96     1.7%   [0.3%–3.4%]   markov\n$   466.92     0.7%   [0.1%–1.7%]   markov\n$   473.97     0.3%   [0.0%–0.8%]   markov\n$   481.14     0.1%   [0.0%–0.3%]   markov","expiresAt":1774959163116,"toolName":"markov_distribution","savedAt":"2026-03-31T11:57:43.116Z"}