{"key":"polymarket_search:{\"limit\":8,\"query\":\"Iran war\"}","value":"{\"data\":{\"result\":\"Polymarket — prediction market probabilities for: \\\"Iran war\\\"\\n(Prices reflect crowd-sourced odds from real-money traders)\\n\\n▸ Iran x Israel/US conflict ends by April 7?\\n    Yes: 1.6%\\n    No: 98.4%\\n    expires 2026-04-07 · 24h vol $300K · liquidity $186K · age 8d\\n\\n▸ Iran x Israel/US conflict ends by April 15?\\n    Yes: 7.5%\\n    No: 92.5%\\n    expires 2026-04-15 · 24h vol $299K · liquidity $80K · age 20d\\n\\n▸ Iran x Israel/US conflict ends by April 30?\\n    Yes: 25.5%\\n    No: 74.5%\\n    expires 2026-04-30 · 24h vol $283K · liquidity $51K · age 20d\\n\\n▸ Iran x Israel/US conflict ends by March 31?\\n    Yes: 0.1%\\n    No: 100.0%\\n    expires 2026-03-31 · 24h vol $257K · liquidity $556K · age 32d\\n\\n▸ Will the Iranian regime fall by June 30?\\n    Yes: 11.5%\\n    No: 88.5%\\n    expires 2026-06-30 · 24h vol $803K · liquidity $1.6M · age 105d\\n\\n▸ Will the Iranian regime fall before 2027?\\n    Yes: 23.5%\\n    No: 76.5%\\n    expires 2026-12-31 · 24h vol $268K · liquidity $401K · age 149d\\n\\n▸ Will Iran strike Bahrain again in March?\\n    Yes: 100.0%\\n    No: 0.1%\\n    expires 2026-03-07 · 24h vol $193K · liquidity $593K · age 15d\\n\\n▸ Will Iran strike UAE again in March?\\n    Yes: 72.6%\\n    No: 27.4%\\n    expires 2026-03-07 · 24h vol $13K · liquidity $11K · age 15d\\n\\nSource: polymarket.com — probabilities are market-implied, not guaranteed.\"}}","expiresAt":1775133760588,"toolName":"polymarket_search","savedAt":"2026-04-02T12:27:40.588Z"}